brawlstats/__init__.py
brawlstats/core.py
brawlstats/errors.py
brawlstats/utils.py
brawlstats-2.0.0.dist-info/LICENSE
brawlstats-2.0.0.dist-info/METADATA
brawlstats-2.0.0.dist-info/WHEEL
brawlstats-2.0.0.dist-info/top_level.txt
brawlstats-2.0.0.dist-info/RECORD
