Metadata-Version: 2.1
Name: brawlstats
Version: 2.0.0
Summary: An async Python API wrapper for the unofficial Brawl Stars API
Home-page: https://github.com/SharpBit/brawlstats
Author: SharpBit
Author-email: sharpbit3618@gmail.com
License: MIT
Keywords: brawl stars, brawlstats, api-wrapper, async
Platform: UNKNOWN
Requires-Dist: aiohttp
Requires-Dist: python-box
